Workbook

Sheet Setup
A1: Control Ejecutivo de Presupuesto — Proyecto TI (Dual Moneda USD/COP)
A3: Parámetros
A5: Nombre del proyecto | B5: Proyecto Atlas | D5: Tip
A6: Moneda base (referencial) | B6: USD | D6: Dual moneda: registra gastos en USD o COP. El sistema normaliza todo a USD y también muestra COP usando la TRM. Celdas azules = inputs.
A7: TRM (COP por USD) | B7: 4100
A8: Presupuesto máximo (USD) [input] | B8: 250000
A9: Presupuesto máximo (COP) [calc] | B9: =B8*B7
A10: Fecha inicio | B10: 2026-01-01
A11: Mes de reporte (YYYY-MM) | B11: 2026-01
A12: Umbral amarillo (% gasto) | B12: 0.8
A13: Umbral rojo (% gasto) | B13: 0.95
A14: Vista de dashboard | B14: AMBAS

Sheet Recursos
A1: Catálogo de recursos (perfiles por hora)
A2: ID Recurso | B2: Rol | C2: Proveedor | D2: Rate USD/Hr | E2: Rate COP/Hr (calc) | F2: Notas
A3: R-001 | B3: PM / Scrum Master | C3: Vendor A | D3: 55 | E3: =IF(D3="","",D3*Setup!$B$7)
A4: R-002 | B4: Tech Lead | C4: Vendor A | D4: 85 | E4: =IF(D4="","",D4*Setup!$B$7)
A5: R-003 | B5: Backend Dev | C5: Vendor B | D5: 65 | E5: =IF(D5="","",D5*Setup!$B$7)
A6: R-004 | B6: QA Automation | C6: Vendor B | D6: 50 | E6: =IF(D6="","",D6*Setup!$B$7)
A7: R-005 | B7: Data Engineer | C7: Vendor C | D7: 75 | E7: =IF(D7="","",D7*Setup!$B$7)
E8: =IF(D8="","",D8*Setup!$B$7)
E9: =IF(D9="","",D9*Setup!$B$7)
E10: =IF(D10="","",D10*Setup!$B$7)
E11: =IF(D11="","",D11*Setup!$B$7)
E12: =IF(D12="","",D12*Setup!$B$7)
E13: =IF(D13="","",D13*Setup!$B$7)
E14: =IF(D14="","",D14*Setup!$B$7)
E15: =IF(D15="","",D15*Setup!$B$7)
E16: =IF(D16="","",D16*Setup!$B$7)
E17: =IF(D17="","",D17*Setup!$B$7)
E18: =IF(D18="","",D18*Setup!$B$7)
E19: =IF(D19="","",D19*Setup!$B$7)
... E100: =IF(D100="","",D100*Setup!$B$7)

Sheet Plan_Horas
A1: Plan de horas (presupuesto) — por recurso y por mes (Dual Moneda)
A2: ID Recurso | B2: Rol | C2: Rate USD/Hr | D2: Rate COP/Hr | E2: M1 | F2: M2 | G2: M3 | H2: M4 | I2: M5 | J2: M6 | K2: M7 | L2: M8 | M2: M9 | N2: M10 | O2: M11 | P2: M12 | Q2: Total Horas | R2: Budget USD | S2: Budget COP
B3: =IFERROR(VLOOKUP(A3,Recursos!$A$3:$F$100,2,FALSE),"") | C3: =IFERROR(VLOOKUP(A3,Recursos!$A$3:$F$100,4,FALSE),"") | D3: =IFERROR(VLOOKUP(A3,Recursos!$A$3:$F$100,5,FALSE),"") | E3: 0 | F3: 0 | G3: 0 | H3: 0 | I3: 0 | J3: 0 | K3: 0 | L3: 0 | M3: 0 | N3: 0 | O3: 0 | P3: 0 | Q3: =SUM(E3:P3) | R3: =Q3*C3 | S3: =R3*Setup!$B$7
B4: =IFERROR(VLOOKUP(A4,Recursos!$A$3:$F$100,2,FALSE),"") | C4: =IFERROR(VLOOKUP(A4,Recursos!$A$3:$F$100,4,FALSE),"") | D4: =IFERROR(VLOOKUP(A4,Recursos!$A$3:$F$100,5,FALSE),"") | E4: 0 | F4: 0 | G4: 0 | H4: 0 | I4: 0 | J4: 0 | K4: 0 | L4: 0 | M4: 0 | N4: 0 | O4: 0 | P4: 0 | Q4: =SUM(E4:P4) | R4: =Q4*C4 | S4: =R4*Setup!$B$7
B5: =IFERROR(VLOOKUP(A5,Recursos!$A$3:$F$100,2,FALSE),"") | C5: =IFERROR(VLOOKUP(A5,Recursos!$A$3:$F$100,4,FALSE),"") | D5: =IFERROR(VLOOKUP(A5,Recursos!$A$3:$F$100,5,FALSE),"") | E5: 0 | F5: 0 | G5: 0 | H5: 0 | I5: 0 | J5: 0 | K5: 0 | L5: 0 | M5: 0 | N5: 0 | O5: 0 | P5: 0 | Q5: =SUM(E5:P5) | R5: =Q5*C5 | S5: =R5*Setup!$B$7
B6: =IFERROR(VLOOKUP(A6,Recursos!$A$3:$F$100,2,FALSE),"") | C6: =IFERROR(VLOOKUP(A6,Recursos!$A$3:$F$100,4,FALSE),"") | D6: =IFERROR(VLOOKUP(A6,Recursos!$A$3:$F$100,5,FALSE),"") | E6: 0 | F6: 0 | G6: 0 | H6: 0 | I6: 0 | J6: 0 | K6: 0 | L6: 0 | M6: 0 | N6: 0 | O6: 0 | P6: 0 | Q6: =SUM(E6:P6) | R6: =Q6*C6 | S6: =R6*Setup!$B$7
B7: =IFERROR(VLOOKUP(A7,Recursos!$A$3:$F$100,2,FALSE),"") | C7: =IFERROR(VLOOKUP(A7,Recursos!$A$3:$F$100,4,FALSE),"") | D7: =IFERROR(VLOOKUP(A7,Recursos!$A$3:$F$100,5,FALSE),"") | E7: 0 | F7: 0 | G7: 0 | H7: 0 | I7: 0 | J7: 0 | K7: 0 | L7: 0 | M7: 0 | N7: 0 | O7: 0 | P7: 0 | Q7: =SUM(E7:P7) | R7: =Q7*C7 | S7: =R7*Setup!$B$7
B8: =IFERROR(VLOOKUP(A8,Recursos!$A$3:$F$100,2,FALSE),"") | C8: =IFERROR(VLOOKUP(A8,Recursos!$A$3:$F$100,4,FALSE),"") | D8: =IFERROR(VLOOKUP(A8,Recursos!$A$3:$F$100,5,FALSE),"") | E8: 0 | F8: 0 | G8: 0 | H8: 0 | I8: 0 | J8: 0 | K8: 0 | L8: 0 | M8: 0 | N8: 0 | O8: 0 | P8: 0 | Q8: =SUM(E8:P8) | R8: =Q8*C8 | S8: =R8*Setup!$B$7
B9: =IFERROR(VLOOKUP(A9,Recursos!$A$3:$F$100,2,FALSE),"") | C9: =IFERROR(VLOOKUP(A9,Recursos!$A$3:$F$100,4,FALSE),"") | D9: =IFERROR(VLOOKUP(A9,Recursos!$A$3:$F$100,5,FALSE),"") | E9: 0 | F9: 0 | G9: 0 | H9: 0 | I9: 0 | J9: 0 | K9: 0 | L9: 0 | M9: 0 | N9: 0 | O9: 0 | P9: 0 | Q9: =SUM(E9:P9) | R9: =Q9*C9 | S9: =R9*Setup!$B$7
B10: =IFERROR(VLOOKUP(A10,Recursos!$A$3:$F$100,2,FALSE),"") | C10: =IFERROR(VLOOKUP(A10,Recursos!$A$3:$F$100,4,FALSE),"") | D10: =IFERROR(VLOOKUP(A10,Recursos!$A$3:$F$100,5,FALSE),"") | E10: 0 | F10: 0 | G10: 0 | H10: 0 | I10: 0 | J10: 0 | K10: 0 | L10: 0 | M10: 0 | N10: 0 | O10: 0 | P10: 0 | Q10: =SUM(E10:P10) | R10: =Q10*C10 | S10: =R10*Setup!$B$7
B11: =IFERROR(VLOOKUP(A11,Recursos!$A$3:$F$100,2,FALSE),"") | C11: =IFERROR(VLOOKUP(A11,Recursos!$A$3:$F$100,4,FALSE),"") | D11: =IFERROR(VLOOKUP(A11,Recursos!$A$3:$F$100,5,FALSE),"") | E11: 0 | F11: 0 | G11: 0 | H11: 0 | I11: 0 | J11: 0 | K11: 0 | L11: 0 | M11: 0 | N11: 0 | O11: 0 | P11: 0 | Q11: =SUM(E11:P11) | R11: =Q11*C11 | S11: =R11*Setup!$B$7
B12: =IFERROR(VLOOKUP(A12,Recursos!$A$3:$F$100,2,FALSE),"") | C12: =IFERROR(VLOOKUP(A12,Recursos!$A$3:$F$100,4,FALSE),"") | D12: =IFERROR(VLOOKUP(A12,Recursos!$A$3:$F$100,5,FALSE),"") | E12: 0 | F12: 0 | G12: 0 | H12: 0 | I12: 0 | J12: 0 | K12: 0 | L12: 0 | M12: 0 | N12: 0 | O12: 0 | P12: 0 | Q12: =SUM(E12:P12) | R12: =Q12*C12 | S12: =R12*Setup!$B$7
B13: =IFERROR(VLOOKUP(A13,Recursos!$A$3:$F$100,2,FALSE),"") | C13: =IFERROR(VLOOKUP(A13,Recursos!$A$3:$F$100,4,FALSE),"") | D13: =IFERROR(VLOOKUP(A13,Recursos!$A$3:$F$100,5,FALSE),"") | E13: 0 | F13: 0 | G13: 0 | H13: 0 | I13: 0 | J13: 0 | K13: 0 | L13: 0 | M13: 0 | N13: 0 | O13: 0 | P13: 0 | Q13: =SUM(E13:P13) | R13: =Q13*C13 | S13: =R13*Setup!$B$7
B14: =IFERROR(VLOOKUP(A14,Recursos!$A$3:$F$100,2,FALSE),"") | C14: =IFERROR(VLOOKUP(A14,Recursos!$A$3:$F$100,4,FALSE),"") | D14: =IFERROR(VLOOKUP(A14,Recursos!$A$3:$F$100,5,FALSE),"") | E14: 0 | F14: 0 | G14: 0 | H14: 0 | I14: 0 | J14: 0 | K14: 0 | L14: 0 | M14: 0 | N14: 0 | O14: 0 | P14: 0 | Q14: =SUM(E14:P14) | R14: =Q14*C14 | S14: =R14*Setup!$B$7
... B52: =IFERROR(VLOOKUP(A52,Recursos!$A$3:$F$100,2,FALSE),"") | C52: =IFERROR(VLOOKUP(A52,Recursos!$A$3:$F$100,4,FALSE),"") | D52: =IFERROR(VLOOKUP(A52,Recursos!$A$3:$F$100,5,FALSE),"") | E52: 0 | F52: 0 | G52: 0 | H52: 0 | I52: 0 | J52: 0 | K52: 0 | L52: 0 | M52: 0 | N52: 0 | O52: 0 | P52: 0 | Q52: =SUM(E52:P52) | R52: =Q52*C52 | S52: =R52*Setup!$B$7

Sheet Gastos_Actuales
A1: Registro de gastos (actuales) — USD o COP (dual moneda)
A2: Fecha | B2: Mes (YYYY-MM) | C2: Moneda (USD/COP) | D2: ID Recurso | E2: Rol | F2: Categoría | G2: Descripción | H2: Horas | I2: Rate (moneda) | J2: Monto Manual (moneda) | K2: Monto USD (calc) | L2: Monto COP (calc) | M2: Factura/OC | N2: Aprobado (S/N) | O2: Responsable | P2: Notas
B3: =IF(A3="","",TEXT(A3,"yyyy-mm")) | C3: USD | E3: =IFERROR(VLOOKUP(D3,Recursos!$A$3:$F$100,2,FALSE),"") | H3: 0 | I3: =IF(F3="Labor",IF(C3="USD",IFERROR(VLOOKUP(D3,Recursos!$A$3:$F$100,4,FALSE),""),IFERROR(VLOOKUP(D3,Recursos!$A$3:$F$100,5,FALSE),"")),"") | J3: 0 | K3: =IF(F3="Labor",IF(C3="USD",H3*I3,(H3*I3)/Setup!$B$7),IF(C3="USD",J3,J3/Setup!$B$7)) | L3: =K3*Setup!$B$7 | N3: S
B4: =IF(A4="","",TEXT(A4,"yyyy-mm")) | C4: USD | E4: =IFERROR(VLOOKUP(D4,Recursos!$A$3:$F$100,2,FALSE),"") | H4: 0 | I4: =IF(F4="Labor",IF(C4="USD",IFERROR(VLOOKUP(D4,Recursos!$A$3:$F$100,4,FALSE),""),IFERROR(VLOOKUP(D4,Recursos!$A$3:$F$100,5,FALSE),"")),"") | J4: 0 | K4: =IF(F4="Labor",IF(C4="USD",H4*I4,(H4*I4)/Setup!$B$7),IF(C4="USD",J4,J4/Setup!$B$7)) | L4: =K4*Setup!$B$7 | N4: S
B5: =IF(A5="","",TEXT(A5,"yyyy-mm")) | C5: USD | E5: =IFERROR(VLOOKUP(D5,Recursos!$A$3:$F$100,2,FALSE),"") | H5: 0 | I5: =IF(F5="Labor",IF(C5="USD",IFERROR(VLOOKUP(D5,Recursos!$A$3:$F$100,4,FALSE),""),IFERROR(VLOOKUP(D5,Recursos!$A$3:$F$100,5,FALSE),"")),"") | J5: 0 | K5: =IF(F5="Labor",IF(C5="USD",H5*I5,(H5*I5)/Setup!$B$7),IF(C5="USD",J5,J5/Setup!$B$7)) | L5: =K5*Setup!$B$7 | N5: S
B6: =IF(A6="","",TEXT(A6,"yyyy-mm")) | C6: USD | E6: =IFERROR(VLOOKUP(D6,Recursos!$A$3:$F$100,2,FALSE),"") | H6: 0 | I6: =IF(F6="Labor",IF(C6="USD",IFERROR(VLOOKUP(D6,Recursos!$A$3:$F$100,4,FALSE),""),IFERROR(VLOOKUP(D6,Recursos!$A$3:$F$100,5,FALSE),"")),"") | J6: 0 | K6: =IF(F6="Labor",IF(C6="USD",H6*I6,(H6*I6)/Setup!$B$7),IF(C6="USD",J6,J6/Setup!$B$7)) | L6: =K6*Setup!$B$7 | N6: S
B7: =IF(A7="","",TEXT(A7,"yyyy-mm")) | C7: USD | E7: =IFERROR(VLOOKUP(D7,Recursos!$A$3:$F$100,2,FALSE),"") | H7: 0 | I7: =IF(F7="Labor",IF(C7="USD",IFERROR(VLOOKUP(D7,Recursos!$A$3:$F$100,4,FALSE),""),IFERROR(VLOOKUP(D7,Recursos!$A$3:$F$100,5,FALSE),"")),"") | J7: 0 | K7: =IF(F7="Labor",IF(C7="USD",H7*I7,(H7*I7)/Setup!$B$7),IF(C7="USD",J7,J7/Setup!$B$7)) | L7: =K7*Setup!$B$7 | N7: S
B8: =IF(A8="","",TEXT(A8,"yyyy-mm")) | C8: USD | E8: =IFERROR(VLOOKUP(D8,Recursos!$A$3:$F$100,2,FALSE),"") | H8: 0 | I8: =IF(F8="Labor",IF(C8="USD",IFERROR(VLOOKUP(D8,Recursos!$A$3:$F$100,4,FALSE),""),IFERROR(VLOOKUP(D8,Recursos!$A$3:$F$100,5,FALSE),"")),"") | J8: 0 | K8: =IF(F8="Labor",IF(C8="USD",H8*I8,(H8*I8)/Setup!$B$7),IF(C8="USD",J8,J8/Setup!$B$7)) | L8: =K8*Setup!$B$7 | N8: S
B9: =IF(A9="","",TEXT(A9,"yyyy-mm")) | C9: USD | E9: =IFERROR(VLOOKUP(D9,Recursos!$A$3:$F$100,2,FALSE),"") | H9: 0 | I9: =IF(F9="Labor",IF(C9="USD",IFERROR(VLOOKUP(D9,Recursos!$A$3:$F$100,4,FALSE),""),IFERROR(VLOOKUP(D9,Recursos!$A$3:$F$100,5,FALSE),"")),"") | J9: 0 | K9: =IF(F9="Labor",IF(C9="USD",H9*I9,(H9*I9)/Setup!$B$7),IF(C9="USD",J9,J9/Setup!$B$7)) | L9: =K9*Setup!$B$7 | N9: S
B10: =IF(A10="","",TEXT(A10,"yyyy-mm")) | C10: USD | E10: =IFERROR(VLOOKUP(D10,Recursos!$A$3:$F$100,2,FALSE),"") | H10: 0 | I10: =IF(F10="Labor",IF(C10="USD",IFERROR(VLOOKUP(D10,Recursos!$A$3:$F$100,4,FALSE),""),IFERROR(VLOOKUP(D10,Recursos!$A$3:$F$100,5,FALSE),"")),"") | J10: 0 | K10: =IF(F10="Labor",IF(C10="USD",H10*I10,(H10*I10)/Setup!$B$7),IF(C10="USD",J10,J10/Setup!$B$7)) | L10: =K10*Setup!$B$7 | N10: S
B11: =IF(A11="","",TEXT(A11,"yyyy-mm")) | C11: USD | E11: =IFERROR(VLOOKUP(D11,Recursos!$A$3:$F$100,2,FALSE),"") | H11: 0 | I11: =IF(F11="Labor",IF(C11="USD",IFERROR(VLOOKUP(D11,Recursos!$A$3:$F$100,4,FALSE),""),IFERROR(VLOOKUP(D11,Recursos!$A$3:$F$100,5,FALSE),"")),"") | J11: 0 | K11: =IF(F11="Labor",IF(C11="USD",H11*I11,(H11*I11)/Setup!$B$7),IF(C11="USD",J11,J11/Setup!$B$7)) | L11: =K11*Setup!$B$7 | N11: S
B12: =IF(A12="","",TEXT(A12,"yyyy-mm")) | C12: USD | E12: =IFERROR(VLOOKUP(D12,Recursos!$A$3:$F$100,2,FALSE),"") | H12: 0 | I12: =IF(F12="Labor",IF(C12="USD",IFERROR(VLOOKUP(D12,Recursos!$A$3:$F$100,4,FALSE),""),IFERROR(VLOOKUP(D12,Recursos!$A$3:$F$100,5,FALSE),"")),"") | J12: 0 | K12: =IF(F12="Labor",IF(C12="USD",H12*I12,(H12*I12)/Setup!$B$7),IF(C12="USD",J12,J12/Setup!$B$7)) | L12: =K12*Setup!$B$7 | N12: S
B13: =IF(A13="","",TEXT(A13,"yyyy-mm")) | C13: USD | E13: =IFERROR(VLOOKUP(D13,Recursos!$A$3:$F$100,2,FALSE),"") | H13: 0 | I13: =IF(F13="Labor",IF(C13="USD",IFERROR(VLOOKUP(D13,Recursos!$A$3:$F$100,4,FALSE),""),IFERROR(VLOOKUP(D13,Recursos!$A$3:$F$100,5,FALSE),"")),"") | J13: 0 | K13: =IF(F13="Labor",IF(C13="USD",H13*I13,(H13*I13)/Setup!$B$7),IF(C13="USD",J13,J13/Setup!$B$7)) | L13: =K13*Setup!$B$7 | N13: S
B14: =IF(A14="","",TEXT(A14,"yyyy-mm")) | C14: USD | E14: =IFERROR(VLOOKUP(D14,Recursos!$A$3:$F$100,2,FALSE),"") | H14: 0 | I14: =IF(F14="Labor",IF(C14="USD",IFERROR(VLOOKUP(D14,Recursos!$A$3:$F$100,4,FALSE),""),IFERROR(VLOOKUP(D14,Recursos!$A$3:$F$100,5,FALSE),"")),"") | J14: 0 | K14: =IF(F14="Labor",IF(C14="USD",H14*I14,(H14*I14)/Setup!$B$7),IF(C14="USD",J14,J14/Setup!$B$7)) | L14: =K14*Setup!$B$7 | N14: S
... B302: =IF(A302="","",TEXT(A302,"yyyy-mm")) | C302: USD | E302: =IFERROR(VLOOKUP(D302,Recursos!$A$3:$F$100,2,FALSE),"") | H302: 0 | I302: =IF(F302="Labor",IF(C302="USD",IFERROR(VLOOKUP(D302,Recursos!$A$3:$F$100,4,FALSE),""),IFERROR(VLOOKUP(D302,Recursos!$A$3:$F$100,5,FALSE),"")),"") | J302: 0 | K302: =IF(F302="Labor",IF(C302="USD",H302*I302,(H302*I302)/Setup!$B$7),IF(C302="USD",J302,J302/Setup!$B$7)) | L302: =K302*Setup!$B$7 | N302: S

Sheet Resumen
A1: Resumen mensual — Budget vs Actual (USD y COP) + proyección
A2: Mes | B2: Budget USD | C2: Actual USD | D2: % Consumido (USD) | E2: Budget Acum USD | F2: Actual Acum USD | G2: Var USD | H2: EAC USD | I2: %EAC/Budget (USD) | J2: Budget COP | K2: Actual COP | L2: % Consumido (COP) | M2: Budget Acum COP | N2: Actual Acum COP | O2: Var COP | P2: EAC COP | Q2: %EAC/Budget (COP)
A3: 2026-01 | B3: =SUMPRODUCT(Plan_Horas!$E$3:$E$52,Plan_Horas!$C$3:$C$52) | C3: =SUMIFS(Gastos_Actuales!$K:$K,Gastos_Actuales!$B:$B,$A3) | D3: =IF(B3=0,0,C3/B3) | E3: =SUM($B$3:B3) | F3: =SUM($C$3:C3) | G3: =F3-E3 | H3: =F3+(SUM($B$3:$B$14)-E3) | I3: =IF(SUM($B$3:$B$14)=0,0,H3/SUM($B$3:$B$14)) | J3: =B3*Setup!$B$7 | K3: =C3*Setup!$B$7 | L3: =IF(J3=0,0,K3/J3) | M3: =E3*Setup!$B$7 | N3: =F3*Setup!$B$7 | O3: =N3-M3 | P3: =H3*Setup!$B$7 | Q3: =IF(SUM($J$3:$J$14)=0,0,P3/SUM($J$3:$J$14))
A4: 2026-02 | B4: =SUMPRODUCT(Plan_Horas!$F$3:$F$52,Plan_Horas!$C$3:$C$52) | C4: =SUMIFS(Gastos_Actuales!$K:$K,Gastos_Actuales!$B:$B,$A4) | D4: =IF(B4=0,0,C4/B4) | E4: =SUM($B$3:B4) | F4: =SUM($C$3:C4) | G4: =F4-E4 | H4: =F4+(SUM($B$3:$B$14)-E4) | I4: =IF(SUM($B$3:$B$14)=0,0,H4/SUM($B$3:$B$14)) | J4: =B4*Setup!$B$7 | K4: =C4*Setup!$B$7 | L4: =IF(J4=0,0,K4/J4) | M4: =E4*Setup!$B$7 | N4: =F4*Setup!$B$7 | O4: =N4-M4 | P4: =H4*Setup!$B$7 | Q4: =IF(SUM($J$3:$J$14)=0,0,P4/SUM($J$3:$J$14))
A5: 2026-03 | B5: =SUMPRODUCT(Plan_Horas!$G$3:$G$52,Plan_Horas!$C$3:$C$52) | C5: =SUMIFS(Gastos_Actuales!$K:$K,Gastos_Actuales!$B:$B,$A5) | D5: =IF(B5=0,0,C5/B5) | E5: =SUM($B$3:B5) | F5: =SUM($C$3:C5) | G5: =F5-E5 | H5: =F5+(SUM($B$3:$B$14)-E5) | I5: =IF(SUM($B$3:$B$14)=0,0,H5/SUM($B$3:$B$14)) | J5: =B5*Setup!$B$7 | K5: =C5*Setup!$B$7 | L5: =IF(J5=0,0,K5/J5) | M5: =E5*Setup!$B$7 | N5: =F5*Setup!$B$7 | O5: =N5-M5 | P5: =H5*Setup!$B$7 | Q5: =IF(SUM($J$3:$J$14)=0,0,P5/SUM($J$3:$J$14))
A6: 2026-04 | B6: =SUMPRODUCT(Plan_Horas!$H$3:$H$52,Plan_Horas!$C$3:$C$52) | C6: =SUMIFS(Gastos_Actuales!$K:$K,Gastos_Actuales!$B:$B,$A6) | D6: =IF(B6=0,0,C6/B6) | E6: =SUM($B$3:B6) | F6: =SUM($C$3:C6) | G6: =F6-E6 | H6: =F6+(SUM($B$3:$B$14)-E6) | I6: =IF(SUM($B$3:$B$14)=0,0,H6/SUM($B$3:$B$14)) | J6: =B6*Setup!$B$7 | K6: =C6*Setup!$B$7 | L6: =IF(J6=0,0,K6/J6) | M6: =E6*Setup!$B$7 | N6: =F6*Setup!$B$7 | O6: =N6-M6 | P6: =H6*Setup!$B$7 | Q6: =IF(SUM($J$3:$J$14)=0,0,P6/SUM($J$3:$J$14))
A7: 2026-05 | B7: =SUMPRODUCT(Plan_Horas!$I$3:$I$52,Plan_Horas!$C$3:$C$52) | C7: =SUMIFS(Gastos_Actuales!$K:$K,Gastos_Actuales!$B:$B,$A7) | D7: =IF(B7=0,0,C7/B7) | E7: =SUM($B$3:B7) | F7: =SUM($C$3:C7) | G7: =F7-E7 | H7: =F7+(SUM($B$3:$B$14)-E7) | I7: =IF(SUM($B$3:$B$14)=0,0,H7/SUM($B$3:$B$14)) | J7: =B7*Setup!$B$7 | K7: =C7*Setup!$B$7 | L7: =IF(J7=0,0,K7/J7) | M7: =E7*Setup!$B$7 | N7: =F7*Setup!$B$7 | O7: =N7-M7 | P7: =H7*Setup!$B$7 | Q7: =IF(SUM($J$3:$J$14)=0,0,P7/SUM($J$3:$J$14))
A8: 2026-06 | B8: =SUMPRODUCT(Plan_Horas!$J$3:$J$52,Plan_Horas!$C$3:$C$52) | C8: =SUMIFS(Gastos_Actuales!$K:$K,Gastos_Actuales!$B:$B,$A8) | D8: =IF(B8=0,0,C8/B8) | E8: =SUM($B$3:B8) | F8: =SUM($C$3:C8) | G8: =F8-E8 | H8: =F8+(SUM($B$3:$B$14)-E8) | I8: =IF(SUM($B$3:$B$14)=0,0,H8/SUM($B$3:$B$14)) | J8: =B8*Setup!$B$7 | K8: =C8*Setup!$B$7 | L8: =IF(J8=0,0,K8/J8) | M8: =E8*Setup!$B$7 | N8: =F8*Setup!$B$7 | O8: =N8-M8 | P8: =H8*Setup!$B$7 | Q8: =IF(SUM($J$3:$J$14)=0,0,P8/SUM($J$3:$J$14))
A9: 2026-07 | B9: =SUMPRODUCT(Plan_Horas!$K$3:$K$52,Plan_Horas!$C$3:$C$52) | C9: =SUMIFS(Gastos_Actuales!$K:$K,Gastos_Actuales!$B:$B,$A9) | D9: =IF(B9=0,0,C9/B9) | E9: =SUM($B$3:B9) | F9: =SUM($C$3:C9) | G9: =F9-E9 | H9: =F9+(SUM($B$3:$B$14)-E9) | I9: =IF(SUM($B$3:$B$14)=0,0,H9/SUM($B$3:$B$14)) | J9: =B9*Setup!$B$7 | K9: =C9*Setup!$B$7 | L9: =IF(J9=0,0,K9/J9) | M9: =E9*Setup!$B$7 | N9: =F9*Setup!$B$7 | O9: =N9-M9 | P9: =H9*Setup!$B$7 | Q9: =IF(SUM($J$3:$J$14)=0,0,P9/SUM($J$3:$J$14))
A10: 2026-08 | B10: =SUMPRODUCT(Plan_Horas!$L$3:$L$52,Plan_Horas!$C$3:$C$52) | C10: =SUMIFS(Gastos_Actuales!$K:$K,Gastos_Actuales!$B:$B,$A10) | D10: =IF(B10=0,0,C10/B10) | E10: =SUM($B$3:B10) | F10: =SUM($C$3:C10) | G10: =F10-E10 | H10: =F10+(SUM($B$3:$B$14)-E10) | I10: =IF(SUM($B$3:$B$14)=0,0,H10/SUM($B$3:$B$14)) | J10: =B10*Setup!$B$7 | K10: =C10*Setup!$B$7 | L10: =IF(J10=0,0,K10/J10) | M10: =E10*Setup!$B$7 | N10: =F10*Setup!$B$7 | O10: =N10-M10 | P10: =H10*Setup!$B$7 | Q10: =IF(SUM($J$3:$J$14)=0,0,P10/SUM($J$3:$J$14))
A11: 2026-09 | B11: =SUMPRODUCT(Plan_Horas!$M$3:$M$52,Plan_Horas!$C$3:$C$52) | C11: =SUMIFS(Gastos_Actuales!$K:$K,Gastos_Actuales!$B:$B,$A11) | D11: =IF(B11=0,0,C11/B11) | E11: =SUM($B$3:B11) | F11: =SUM($C$3:C11) | G11: =F11-E11 | H11: =F11+(SUM($B$3:$B$14)-E11) | I11: =IF(SUM($B$3:$B$14)=0,0,H11/SUM($B$3:$B$14)) | J11: =B11*Setup!$B$7 | K11: =C11*Setup!$B$7 | L11: =IF(J11=0,0,K11/J11) | M11: =E11*Setup!$B$7 | N11: =F11*Setup!$B$7 | O11: =N11-M11 | P11: =H11*Setup!$B$7 | Q11: =IF(SUM($J$3:$J$14)=0,0,P11/SUM($J$3:$J$14))
A12: 2026-10 | B12: =SUMPRODUCT(Plan_Horas!$N$3:$N$52,Plan_Horas!$C$3:$C$52) | C12: =SUMIFS(Gastos_Actuales!$K:$K,Gastos_Actuales!$B:$B,$A12) | D12: =IF(B12=0,0,C12/B12) | E12: =SUM($B$3:B12) | F12: =SUM($C$3:C12) | G12: =F12-E12 | H12: =F12+(SUM($B$3:$B$14)-E12) | I12: =IF(SUM($B$3:$B$14)=0,0,H12/SUM($B$3:$B$14)) | J12: =B12*Setup!$B$7 | K12: =C12*Setup!$B$7 | L12: =IF(J12=0,0,K12/J12) | M12: =E12*Setup!$B$7 | N12: =F12*Setup!$B$7 | O12: =N12-M12 | P12: =H12*Setup!$B$7 | Q12: =IF(SUM($J$3:$J$14)=0,0,P12/SUM($J$3:$J$14))
A13: 2026-11 | B13: =SUMPRODUCT(Plan_Horas!$O$3:$O$52,Plan_Horas!$C$3:$C$52) | C13: =SUMIFS(Gastos_Actuales!$K:$K,Gastos_Actuales!$B:$B,$A13) | D13: =IF(B13=0,0,C13/B13) | E13: =SUM($B$3:B13) | F13: =SUM($C$3:C13) | G13: =F13-E13 | H13: =F13+(SUM($B$3:$B$14)-E13) | I13: =IF(SUM($B$3:$B$14)=0,0,H13/SUM($B$3:$B$14)) | J13: =B13*Setup!$B$7 | K13: =C13*Setup!$B$7 | L13: =IF(J13=0,0,K13/J13) | M13: =E13*Setup!$B$7 | N13: =F13*Setup!$B$7 | O13: =N13-M13 | P13: =H13*Setup!$B$7 | Q13: =IF(SUM($J$3:$J$14)=0,0,P13/SUM($J$3:$J$14))
A14: 2026-12 | B14: =SUMPRODUCT(Plan_Horas!$P$3:$P$52,Plan_Horas!$C$3:$C$52) | C14: =SUMIFS(Gastos_Actuales!$K:$K,Gastos_Actuales!$B:$B,$A14) | D14: =IF(B14=0,0,C14/B14) | E14: =SUM($B$3:B14) | F14: =SUM($C$3:C14) | G14: =F14-E14 | H14: =F14+(SUM($B$3:$B$14)-E14) | I14: =IF(SUM($B$3:$B$14)=0,0,H14/SUM($B$3:$B$14)) | J14: =B14*Setup!$B$7 | K14: =C14*Setup!$B$7 | L14: =IF(J14=0,0,K14/J14) | M14: =E14*Setup!$B$7 | N14: =F14*Setup!$B$7 | O14: =N14-M14 | P14: =H14*Setup!$B$7 | Q14: =IF(SUM($J$3:$J$14)=0,0,P14/SUM($J$3:$J$14))

Sheet Dashboard
A1: Dashboard Ejecutivo — Dual Moneda + Semáforos + Proyección
A3: Presupuesto (USD) | D3: Actual (USD) | G3: Disponible (USD) | J3: % Consumido (USD)
A4: =Setup!$B$8 | D4: =SUM(Gastos_Actuales!$K:$K) | G4: =A4-D4 | J4: =IF(A4=0,0,D4/A4)
A6: Presupuesto (COP) | D6: Actual (COP) | G6: Disponible (COP) | J6: % Consumido (COP)
A7: =Setup!$B$9 | D7: =SUM(Gastos_Actuales!$L:$L) | G7: =A7-D7 | J7: =IF(A7=0,0,D7/A7)
A9: Proyección (EAC)
A10: EAC USD (según Mes de reporte) | G10: EAC COP (según Mes de reporte)
A11: =INDEX(Resumen!$H$3:$H$14, MATCH(Setup!$B$12, Resumen!$A$3:$A$14, 0)) | G11: =INDEX(Resumen!$P$3:$P$14, MATCH(Setup!$B$12, Resumen!$A$3:$A$14, 0))
A13: • Consejo ejecutivo: si el gasto viene en COP, la TRM manda. Si cambia mucho, tu presupuesto 'sube' o 'baja' sin pedir permiso.
A15: Tendencia (USD): Acumulado Actual vs Budget | G15: Mix mensual (USD): Labor vs No-Labor
A17: Mes | B17: Budget Acum USD | C17: Actual Acum USD | G17: Mes | H17: Labor USD | I17: No-Labor USD
A18: =Resumen!A3 | B18: =Resumen!E3 | C18: =Resumen!F3 | G18: =Resumen!A3 | H18: =SUMIFS(Gastos_Actuales!$K:$K,Gastos_Actuales!$B:$B,Resumen!A3,Gastos_Actuales!$F:$F,"Labor") | I18: =SUMIFS(Gastos_Actuales!$K:$K,Gastos_Actuales!$B:$B,Resumen!A3,Gastos_Actuales!$F:$F,"<>Labor")
A19: =Resumen!A4 | B19: =Resumen!E4 | C19: =Resumen!F4 | G19: =Resumen!A4 | H19: =SUMIFS(Gastos_Actuales!$K:$K,Gastos_Actuales!$B:$B,Resumen!A4,Gastos_Actuales!$F:$F,"Labor") | I19: =SUMIFS(Gastos_Actuales!$K:$K,Gastos_Actuales!$B:$B,Resumen!A4,Gastos_Actuales!$F:$F,"<>Labor")
A20: =Resumen!A5 | B20: =Resumen!E5 | C20: =Resumen!F5 | G20: =Resumen!A5 | H20: =SUMIFS(Gastos_Actuales!$K:$K,Gastos_Actuales!$B:$B,Resumen!A5,Gastos_Actuales!$F:$F,"Labor") | I20: =SUMIFS(Gastos_Actuales!$K:$K,Gastos_Actuales!$B:$B,Resumen!A5,Gastos_Actuales!$F:$F,"<>Labor")
A21: =Resumen!A6 | B21: =Resumen!E6 | C21: =Resumen!F6 | G21: =Resumen!A6 | H21: =SUMIFS(Gastos_Actuales!$K:$K,Gastos_Actuales!$B:$B,Resumen!A6,Gastos_Actuales!$F:$F,"Labor") | I21: =SUMIFS(Gastos_Actuales!$K:$K,Gastos_Actuales!$B:$B,Resumen!A6,Gastos_Actuales!$F:$F,"<>Labor")
A22: =Resumen!A7 | B22: =Resumen!E7 | C22: =Resumen!F7 | G22: =Resumen!A7 | H22: =SUMIFS(Gastos_Actuales!$K:$K,Gastos_Actuales!$B:$B,Resumen!A7,Gastos_Actuales!$F:$F,"Labor") | I22: =SUMIFS(Gastos_Actuales!$K:$K,Gastos_Actuales!$B:$B,Resumen!A7,Gastos_Actuales!$F:$F,"<>Labor")
A23: =Resumen!A8 | B23: =Resumen!E8 | C23: =Resumen!F8 | G23: =Resumen!A8 | H23: =SUMIFS(Gastos_Actuales!$K:$K,Gastos_Actuales!$B:$B,Resumen!A8,Gastos_Actuales!$F:$F,"Labor") | I23: =SUMIFS(Gastos_Actuales!$K:$K,Gastos_Actuales!$B:$B,Resumen!A8,Gastos_Actuales!$F:$F,"<>Labor")
A24: =Resumen!A9 | B24: =Resumen!E9 | C24: =Resumen!F9 | G24: =Resumen!A9 | H24: =SUMIFS(Gastos_Actuales!$K:$K,Gastos_Actuales!$B:$B,Resumen!A9,Gastos_Actuales!$F:$F,"Labor") | I24: =SUMIFS(Gastos_Actuales!$K:$K,Gastos_Actuales!$B:$B,Resumen!A9,Gastos_Actuales!$F:$F,"<>Labor")
A25: =Resumen!A10 | B25: =Resumen!E10 | C25: =Resumen!F10 | G25: =Resumen!A10 | H25: =SUMIFS(Gastos_Actuales!$K:$K,Gastos_Actuales!$B:$B,Resumen!A10,Gastos_Actuales!$F:$F,"Labor") | I25: =SUMIFS(Gastos_Actuales!$K:$K,Gastos_Actuales!$B:$B,Resumen!A10,Gastos_Actuales!$F:$F,"<>Labor")
A26: =Resumen!A11 | B26: =Resumen!E11 | C26: =Resumen!F11 | G26: =Resumen!A11 | H26: =SUMIFS(Gastos_Actuales!$K:$K,Gastos_Actuales!$B:$B,Resumen!A11,Gastos_Actuales!$F:$F,"Labor") | I26: =SUMIFS(Gastos_Actuales!$K:$K,Gastos_Actuales!$B:$B,Resumen!A11,Gastos_Actuales!$F:$F,"<>Labor")
A27: =Resumen!A12 | B27: =Resumen!E12 | C27: =Resumen!F12 | G27: =Resumen!A12 | H27: =SUMIFS(Gastos_Actuales!$K:$K,Gastos_Actuales!$B:$B,Resumen!A12,Gastos_Actuales!$F:$F,"Labor") | I27: =SUMIFS(Gastos_Actuales!$K:$K,Gastos_Actuales!$B:$B,Resumen!A12,Gastos_Actuales!$F:$F,"<>Labor")
A28: =Resumen!A13 | B28: =Resumen!E13 | C28: =Resumen!F13 | G28: =Resumen!A13 | H28: =SUMIFS(Gastos_Actuales!$K:$K,Gastos_Actuales!$B:$B,Resumen!A13,Gastos_Actuales!$F:$F,"Labor") | I28: =SUMIFS(Gastos_Actuales!$K:$K,Gastos_Actuales!$B:$B,Resumen!A13,Gastos_Actuales!$F:$F,"<>Labor")
A29: =Resumen!A14 | B29: =Resumen!E14 | C29: =Resumen!F14 | G29: =Resumen!A14 | H29: =SUMIFS(Gastos_Actuales!$K:$K,Gastos_Actuales!$B:$B,Resumen!A14,Gastos_Actuales!$F:$F,"Labor") | I29: =SUMIFS(Gastos_Actuales!$K:$K,Gastos_Actuales!$B:$B,Resumen!A14,Gastos_Actuales!$F:$F,"<>Labor")

Sheet Macro_VBA (opcional)
A1: Macro opcional (copia y pega en Excel) — Budget Guard Dual Moneda
A3: Option Explicit ' === BUDGET GUARD (DUAL MONEDA) === ' - Normaliza a USD usando Setup!B7 (TRM). ' - Alertas en amarillo/rojo para control ejecutivo. ' - Puedes extenderlo para BLOQUEAR registros si pct >= rojo (ver comentario). Public Sub BudgetGuard_Refresh() Dim budgetUSD As Double, actualUSD As Double, pct As Double budgetUSD = Sheets("Setup").Range("B8").Value actualUSD = Application.WorksheetFunction.Sum(Sheets("Gastos_Actuales").Range("K:K")) If budgetUSD <= 0 Then Exit Sub pct = actualUSD / budgetUSD If pct >= Sheets("Setup").Range("B13").Value Then MsgBox "🚨 Presupuesto en ROJO (USD): " & Format(pct, "0%") & vbCrLf & _ "Acción: congela horas no críticas / renegocia alcance.", vbExclamation, "Budget Guard" ' --- (opcional) BLOQUEO --- ' Sheets("Gastos_Actuales").Protect Password:="budget", UserInterfaceOnly:=True ' MsgBox "Hoja bloqueada. Desbloquea al aprobar un Change Request.", vbInformation ElseIf pct >= Sheets("Setup").Range("B12").Value Then MsgBox "⚠️ Presupuesto en AMARILLO (USD): " & Format(pct, "0%") & vbCrLf & _ "Acción: revisa burn rate y ajusta capacidad.", vbInformation, "Budget Guard" End If End Sub ' Pegar este evento dentro del objeto de la hoja "Gastos_Actuales": ' Private Sub Worksheet_Change(ByVal Target As Range) ' On Error GoTo SafeExit ' If Not Intersect(Target, Me.Range("A:P")) Is Nothing Then ' Application.EnableEvents = False ' BudgetGuard_Refresh ' End If ' SafeExit: ' Application.EnableEvents = True ' End Sub

Sheet Dashboard Ejecutivo
A1: KPIs Proyecto
A3: Ingreso Total | B3: =SUM(Detalle por Recurso!H:H)
A4: Costo Total | B4: =SUM(Detalle por Recurso!G:G)
A5: Profit Total | B5: =B3-B4
A6: Margen Global | B6: =IF(B3=0,0,B5/B3)

Sheet Detalle por Recurso
A1: Recurso | B1: Rol | C1: Horas Plan | D1: Horas Reales | E1: Rate Cliente | F1: Costo Hora | G1: Costo Total | H1: Ingreso | I1: Profit | J1: Margen %
G2: =D2*F2 | H2: =D2*E2 | I2: =H2-G2 | J2: =IF(H2=0,0,I2/H2)
G3: =D3*F3 | H3: =D3*E3 | I3: =H3-G3 | J3: =IF(H3=0,0,I3/H3)
G4: =D4*F4 | H4: =D4*E4 | I4: =H4-G4 | J4: =IF(H4=0,0,I4/H4)
G5: =D5*F5 | H5: =D5*E5 | I5: =H5-G5 | J5: =IF(H5=0,0,I5/H5)
G6: =D6*F6 | H6: =D6*E6 | I6: =H6-G6 | J6: =IF(H6=0,0,I6/H6)
G7: =D7*F7 | H7: =D7*E7 | I7: =H7-G7 | J7: =IF(H7=0,0,I7/H7)
G8: =D8*F8 | H8: =D8*E8 | I8: =H8-G8 | J8: =IF(H8=0,0,I8/H8)
G9: =D9*F9 | H9: =D9*E9 | I9: =H9-G9 | J9: =IF(H9=0,0,I9/H9)
G10: =D10*F10 | H10: =D10*E10 | I10: =H10-G10 | J10: =IF(H10=0,0,I10/H10)
G11: =D11*F11 | H11: =D11*E11 | I11: =H11-G11 | J11: =IF(H11=0,0,I11/H11)
G12: =D12*F12 | H12: =D12*E12 | I12: =H12-G12 | J12: =IF(H12=0,0,I12/H12)
G13: =D13*F13 | H13: =D13*E13 | I13: =H13-G13 | J13: =IF(H13=0,0,I13/H13)
... G49: =D49*F49 | H49: =D49*E49 | I49: =H49-G49 | J49: =IF(H49=0,0,I49/H49)

Sheet Gastos por Categoría
A1: Categoría | B1: Presupuesto | C1: Gasto Real | D1: Diferencia | E1: Estado
D2: =B2-C2 | E2: =IF(C2>B2,"🔴","🟢")
D3: =B3-C3 | E3: =IF(C3>B3,"🔴","🟢")
D4: =B4-C4 | E4: =IF(C4>B4,"🔴","🟢")
D5: =B5-C5 | E5: =IF(C5>B5,"🔴","🟢")
D6: =B6-C6 | E6: =IF(C6>B6,"🔴","🟢")
D7: =B7-C7 | E7: =IF(C7>B7,"🔴","🟢")
D8: =B8-C8 | E8: =IF(C8>B8,"🔴","🟢")
D9: =B9-C9 | E9: =IF(C9>B9,"🔴","🟢")
D10: =B10-C10 | E10: =IF(C10>B10,"🔴","🟢")
D11: =B11-C11 | E11: =IF(C11>B11,"🔴","🟢")
D12: =B12-C12 | E12: =IF(C12>B12,"🔴","🟢")
D13: =B13-C13 | E13: =IF(C13>B13,"🔴","🟢")
... D19: =B19-C19 | E19: =IF(C19>B19,"🔴","🟢")
